ecoact_companies/__init__.py
ecoact_companies/db_model/__init__.py
ecoact_companies/domain_model/__init__.py
ecoact_companies-0.0.1.dist-info/METADATA
ecoact_companies-0.0.1.dist-info/WHEEL
ecoact_companies-0.0.1.dist-info/RECORD
